seedrandom/__init__.py
seedrandom/rng.py
seedrandom-2.3.1.dist-info/WHEEL
seedrandom-2.3.1.dist-info/LICENSE
seedrandom-2.3.1.dist-info/METADATA
seedrandom-2.3.1.dist-info/RECORD
