Metadata-Version: 2.1
Name: seedrandom
Version: 2.3.1
Summary: Proof-of-concept seeded RNG lib
Home-page: https://github.com/BananaLoaf/seedrandom
License: MIT
Keywords: random,seed,seeded,number,generator,hash,int,float,bool,bytes,rng,deterministic
Author: BananaLoaf
Author-email: bananaloaf@protonmail.com
Maintainer: BananaLoaf
Maintainer-email: bananaloaf@protonmail.com
Requires-Python: >=3.7,<4.0
Classifier: Development Status :: 5 - Production/Stable
Classifier: Intended Audience :: Developers
Classifier: License :: OSI Approved :: MIT License
Classifier: Operating System :: OS Independent
Classifier: Programming Language :: Python :: 3
Classifier: Programming Language :: Python :: 3.7
Classifier: Programming Language :: Python :: 3.8
Classifier: Programming Language :: Python :: 3.9
Classifier: Programming Language :: Python :: 3.10
Classifier: Programming Language :: Python :: 3.11
Classifier: Programming Language :: Python :: 3
Project-URL: Repository, https://github.com/BananaLoaf/seedrandom
